CTkSimpleMessagebox/Messageboxclass.py
CTkSimpleMessagebox/__init__.py
CTkSimpleMessagebox/test.py
CTkSimpleMessagebox/MessageBoxIcons/ErrorIcon.ico
CTkSimpleMessagebox/MessageBoxIcons/InfoIcon.ico
ctksimplemessagebox-1.2.6.dist-info/licenses/LICENSE
ctksimplemessagebox-1.2.6.dist-info/METADATA
ctksimplemessagebox-1.2.6.dist-info/WHEEL
ctksimplemessagebox-1.2.6.dist-info/top_level.txt
ctksimplemessagebox-1.2.6.dist-info/RECORD
