Metadata-Version: 2.4
Name: ctksimplemessagebox
Version: 1.2.6
Summary: Python Messagebox to display current Infos or Errors.
Author: Scott
Author-email: ctksimplemessagebox@gmail.com
Classifier: Programming Language :: Python :: 3
Classifier: License :: OSI Approved :: MIT License
Classifier: Operating System :: OS Independent
Requires-Python: >=3.6
License-File: LICENSE
Dynamic: author
Dynamic: author-email
Dynamic: classifier
Dynamic: description
Dynamic: description-content-type
Dynamic: license-file
Dynamic: requires-python
Dynamic: summary
